ampq_cl/__init__.py
ampq_cl/__init__.pyc
ampq_cl/logger.py
ampq_cl-0.2.1.data/data/README.rst
ampq_cl-0.2.1.dist-info/METADATA
ampq_cl-0.2.1.dist-info/RECORD
ampq_cl-0.2.1.dist-info/WHEEL
ampq_cl-0.2.1.dist-info/top_level.txt
