Metadata-Version: 2.1
Name: ampq-cl
Version: 0.2.1
Summary: A generic queue client
Home-page: https://github.com/poqweur/ampq_cl
Author: wangjy
Author-email: 1149447019@qq.com
License: Apache License v2
Platform: UNKNOWN
Classifier: Programming Language :: Python
Classifier: Operating System :: Microsoft :: Windows
Classifier: Operating System :: Unix
Classifier: Programming Language :: Python :: 3.6
Classifier: Programming Language :: Python :: 3.7
Requires-Dist: kombu (==3.0.35)
Requires-Dist: pika (==0.13.1)
